<annotation verified="no"><folder>sheep2</folder><filename>folder14__425</filename><path>/Users/nareksahakyan/workspace/manot-internship/photos/sheep2/folder14__425.jpg</path><source><database>Unknown</database></source><size><width>3840</width><height>2160</height><depth>3</depth></size><segmented>0</segmented><object><type>bndbox</type><name>sheep</name><pose>Unspecified</pose><truncated>0</truncated><difficult>1</difficult><bndbox><xmin>1925</xmin><ymin>306</ymin><xmax>1946</xmax><ymax>320</ymax></bndbox></object><object><type>robndbox</type><name>sheep</name><pose>Unspecified</pose><truncated>0</truncated><difficult>1</difficult><robndbox><cx>3331.907</cx><cy>172.7874</cy><w>9.1189</w><h>15.1739</h><angle>0.661593</angle></robndbox></object><object><type>robndbox</type><name>sheep</name><pose>Unspecified</pose><truncated>0</truncated><difficult>1</difficult><robndbox><cx>3320.8167</cx><cy>173.811</cy><w>13.5558</w><h>9.0356</h><angle>2.281593</angle></robndbox></object><object><type>robndbox</type><name>sheep</name><pose>Unspecified</pose><truncated>0</truncated><difficult>1</difficult><robndbox><cx>3460.5241</cx><cy>235.9397</cy><w>24.0262</w><h>14.9647</h><angle>2.301593</angle></robndbox></object><object><type>robndbox</type><name>sheep</name><pose>Unspecified</pose><truncated>0</truncated><difficult>0</difficult><robndbox><cx>3067.9979</cx><cy>793.349</cy><w>25.657</w><h>36.8556</h><angle>3.081593</angle></robndbox></object><object><type>robndbox</type><name>sheep</name><pose>Unspecified</pose><truncated>0</truncated><difficult>0</difficult><robndbox><cx>2876.9759</cx><cy>813.0</cy><w>46.0152</w><h>27.8853</h><angle>0.281593</angle></robndbox></object><object><type>robndbox</type><name>sheep</name><pose>Unspecified</pose><truncated>0</truncated><difficult>0</difficult><robndbox><cx>2805.2254</cx><cy>803.8078</cy><w>44.3199</w><h>27.2011</h><angle>0.31</angle></robndbox></object><object><type>robndbox</type><name>sheep</name><pose>Unspecified</pose><truncated>0</truncated><difficult>0</difficult><robndbox><cx>2717.5953</cx><cy>839.2957</cy><w>38.2527</w><h>27.1927</h><angle>1.1</angle></robndbox></object><object><type>robndbox</type><name>sheep</name><pose>Unspecified</pose><truncated>0</truncated><difficult>0</difficult><robndbox><cx>2711.3752</cx><cy>805.2958</cy><w>32.1448</w><h>21.8213</h><angle>1.79</angle></robndbox></object><object><type>robndbox</type><name>sheep</name><pose>Unspecified</pose><truncated>0</truncated><difficult>0</difficult><robndbox><cx>2464.4711</cx><cy>954.7276</cy><w>28.2848</w><h>42.1107</h><angle>1.791593</angle></robndbox></object><object><type>robndbox</type><name>sheep</name><pose>Unspecified</pose><truncated>0</truncated><difficult>0</difficult><robndbox><cx>2499.9468</cx><cy>788.008</cy><w>30.8681</w><h>26.2066</h><angle>3.011593</angle></robndbox></object><object><type>robndbox</type><name>sheep</name><pose>Unspecified</pose><truncated>0</truncated><difficult>0</difficult><robndbox><cx>2508.301</cx><cy>1015.4781</cy><w>40.2651</w><h>26.9005</h><angle>1.34</angle></robndbox></object><object><type>robndbox</type><name>sheep</name><pose>Unspecified</pose><truncated>0</truncated><difficult>0</difficult><robndbox><cx>2454.7924</cx><cy>1001.0277</cy><w>30.2231</w><h>44.1931</h><angle>1.781593</angle></robndbox></object><object><type>robndbox</type><name>sheep</name><pose>Unspecified</pose><truncated>0</truncated><difficult>0</difficult><robndbox><cx>2403.1077</cx><cy>985.2486</cy><w>26.5159</w><h>40.7238</h><angle>1.801593</angle></robndbox></object><object><type>robndbox</type><name>sheep</name><pose>Unspecified</pose><truncated>0</truncated><difficult>0</difficult><robndbox><cx>1293.4149</cx><cy>1419.7081</cy><w>24.9757</w><h>53.4434</h><angle>0.47</angle></robndbox></object><object><type>robndbox</type><name>sheep</name><pose>Unspecified</pose><truncated>0</truncated><difficult>0</difficult><robndbox><cx>1183.3022</cx><cy>1548.5706</cy><w>44.9652</w><h>25.3306</h><angle>0.851593</angle></robndbox></object><object><type>robndbox</type><name>sheep</name><pose>Unspecified</pose><truncated>0</truncated><difficult>0</difficult><robndbox><cx>1220.284</cx><cy>1433.1655</cy><w>27.5841</w><h>44.1512</h><angle>2.911593</angle></robndbox></object><object><type>robndbox</type><name>sheep</name><pose>Unspecified</pose><truncated>0</truncated><difficult>0</difficult><robndbox><cx>1325.727</cx><cy>1552.4316</cy><w>21.3007</w><h>39.7153</h><angle>0.11</angle></robndbox></object><object><type>robndbox</type><name>sheep</name><pose>Unspecified</pose><truncated>0</truncated><difficult>0</difficult><robndbox><cx>1382.4863</cx><cy>1008.4378</cy><w>47.1077</w><h>25.6836</h><angle>2.641593</angle></robndbox></object><object><type>robndbox</type><name>sheep</name><pose>Unspecified</pose><truncated>0</truncated><difficult>0</difficult><robndbox><cx>1764.7148</cx><cy>1166.7456</cy><w>44.3442</w><h>28.5665</h><angle>0.151593</angle></robndbox></object><object><type>robndbox</type><name>sheep</name><pose>Unspecified</pose><truncated>0</truncated><difficult>0</difficult><robndbox><cx>1800.5263</cx><cy>900.12</cy><w>44.3351</w><h>27.7767</h><angle>2.761593</angle></robndbox></object><object><type>robndbox</type><name>sheep</name><pose>Unspecified</pose><truncated>0</truncated><difficult>0</difficult><robndbox><cx>1988.0224</cx><cy>914.6049</cy><w>23.376</w><h>35.353</h><angle>0.82</angle></robndbox></object><object><type>robndbox</type><name>sheep</name><pose>Unspecified</pose><truncated>0</truncated><difficult>1</difficult><robndbox><cx>1946.9628</cx><cy>1067.0564</cy><w>23.0914</w><h>44.4786</h><angle>1.741593</angle></robndbox></object><object><type>robndbox</type><name>sheep</name><pose>Unspecified</pose><truncated>0</truncated><difficult>0</difficult><robndbox><cx>1442.0677</cx><cy>1500.9939</cy><w>41.1339</w><h>55.746</h><angle>1.721593</angle></robndbox></object><object><type>robndbox</type><name>sheep</name><pose>Unspecified</pose><truncated>0</truncated><difficult>0</difficult><robndbox><cx>2172.5827</cx><cy>1254.6798</cy><w>23.0022</w><h>56.6891</h><angle>0.72</angle></robndbox></object><object><type>robndbox</type><name>sheep</name><pose>Unspecified</pose><truncated>0</truncated><difficult>0</difficult><robndbox><cx>2150.9746</cx><cy>1248.9477</cy><w>20.3137</w><h>32.3132</h><angle>2.951593</angle></robndbox></object><object><type>robndbox</type><name>sheep</name><pose>Unspecified</pose><truncated>0</truncated><difficult>0</difficult><robndbox><cx>2447.9626</cx><cy>1404.0</cy><w>32.6619</w><h>56.3312</h><angle>2.371593</angle></robndbox></object><object><type>robndbox</type><name>sheep</name><pose>Unspecified</pose><truncated>0</truncated><difficult>0</difficult><robndbox><cx>2378.562</cx><cy>927.0935</cy><w>41.6285</w><h>23.1145</h><angle>3.101593</angle></robndbox></object><object><type>robndbox</type><name>sheep</name><pose>Unspecified</pose><truncated>0</truncated><difficult>0</difficult><robndbox><cx>2201.4538</cx><cy>944.0</cy><w>35.6896</w><h>22.9398</h><angle>0.03</angle></robndbox></object><object><type>robndbox</type><name>sheep</name><pose>Unspecified</pose><truncated>0</truncated><difficult>0</difficult><robndbox><cx>2405.8834</cx><cy>1075.2607</cy><w>26.7415</w><h>40.3173</h><angle>1.851593</angle></robndbox></object><object><type>robndbox</type><name>sheep</name><pose>Unspecified</pose><truncated>0</truncated><difficult>0</difficult><robndbox><cx>2797.4595</cx><cy>1496.5</cy><w>47.2798</w><h>87.0808</h><angle>1.801593</angle></robndbox></object><object><type>robndbox</type><name>sheep</name><pose>Unspecified</pose><truncated>0</truncated><difficult>0</difficult><robndbox><cx>2450.2931</cx><cy>1365.3256</cy><w>32.4013</w><h>54.6471</h><angle>2.341593</angle></robndbox></object><object><type>robndbox</type><name>sheep</name><pose>Unspecified</pose><truncated>0</truncated><difficult>0</difficult><robndbox><cx>2415.4082</cx><cy>1443.3196</cy><w>68.2775</w><h>43.2947</h><angle>0.37</angle></robndbox></object><object><type>robndbox</type><name>sheep</name><pose>Unspecified</pose><truncated>0</truncated><difficult>0</difficult><robndbox><cx>2478.161</cx><cy>1353.2419</cy><w>27.1929</w><h>36.9393</h><angle>2.491593</angle></robndbox></object><object><type>robndbox</type><name>sheep</name><pose>Unspecified</pose><truncated>0</truncated><difficult>0</difficult><robndbox><cx>2215.7081</cx><cy>991.1025</cy><w>40.0348</w><h>24.2393</h><angle>0.06</angle></robndbox></object><object><type>robndbox</type><name>sheep</name><pose>Unspecified</pose><truncated>0</truncated><difficult>0</difficult><robndbox><cx>2283.4834</cx><cy>929.1003</cy><w>26.3712</w><h>36.2165</h><angle>1.461593</angle></robndbox></object><object><type>robndbox</type><name>sheep</name><pose>Unspecified</pose><truncated>0</truncated><difficult>0</difficult><robndbox><cx>2094.6315</cx><cy>1025.1007</cy><w>29.0635</w><h>20.0903</h><angle>0.01</angle></robndbox></object><object><type>robndbox</type><name>sheep</name><pose>Unspecified</pose><truncated>0</truncated><difficult>0</difficult><robndbox><cx>2277.7686</cx><cy>1056.4927</cy><w>24.3282</w><h>44.8258</h><angle>0.621593</angle></robndbox></object><object><type>robndbox</type><name>sheep</name><pose>Unspecified</pose><truncated>0</truncated><difficult>0</difficult><robndbox><cx>2172.7341</cx><cy>1087.5732</cy><w>24.7138</w><h>31.8139</h><angle>1.791593</angle></robndbox></object><object><type>robndbox</type><name>sheep</name><pose>Unspecified</pose><truncated>0</truncated><difficult>0</difficult><robndbox><cx>2186.2225</cx><cy>1115.9491</cy><w>25.3382</w><h>44.0184</h><angle>0.61</angle></robndbox></object><object><type>robndbox</type><name>sheep</name><pose>Unspecified</pose><truncated>0</truncated><difficult>0</difficult><robndbox><cx>1350.0005</cx><cy>1331.833</cy><w>36.062</w><h>20.4162</h><angle>0.11</angle></robndbox></object><object><type>robndbox</type><name>sheep</name><pose>Unspecified</pose><truncated>0</truncated><difficult>0</difficult><robndbox><cx>1393.6829</cx><cy>1347.3906</cy><w>25.8071</w><h>35.455</h><angle>1.951593</angle></robndbox></object><object><type>robndbox</type><name>sheep</name><pose>Unspecified</pose><truncated>0</truncated><difficult>0</difficult><robndbox><cx>1190.7082</cx><cy>1635.9845</cy><w>66.4847</w><h>37.7317</h><angle>1.64</angle></robndbox></object><object><type>robndbox</type><name>sheep</name><pose>Unspecified</pose><truncated>0</truncated><difficult>0</difficult><robndbox><cx>1353.3092</cx><cy>1492.6196</cy><w>27.7581</w><h>42.9637</h><angle>2.431593</angle></robndbox></object><object><type>robndbox</type><name>sheep</name><pose>Unspecified</pose><truncated>0</truncated><difficult>0</difficult><robndbox><cx>1168.9494</cx><cy>1522.0</cy><w>29.458</w><h>41.1904</h><angle>2.361593</angle></robndbox></object><object><type>robndbox</type><name>sheep</name><pose>Unspecified</pose><truncated>0</truncated><difficult>0</difficult><robndbox><cx>1590.5593</cx><cy>1245.122</cy><w>47.659</w><h>27.1833</h><angle>0.01</angle></robndbox></object><object><type>robndbox</type><name>sheep</name><pose>Unspecified</pose><truncated>0</truncated><difficult>1</difficult><robndbox><cx>3175.1167</cx><cy>728.5423</cy><w>51.5264</w><h>28.9802</h><angle>0.21</angle></robndbox></object><object><type>robndbox</type><name>sheep</name><pose>Unspecified</pose><truncated>0</truncated><difficult>0</difficult><robndbox><cx>2446.6164</cx><cy>1207.4587</cy><w>33.287</w><h>55.7349</h><angle>2.841593</angle></robndbox></object><object><type>robndbox</type><name>sheep</name><pose>Unspecified</pose><truncated>0</truncated><difficult>0</difficult><robndbox><cx>2250.9368</cx><cy>996.5</cy><w>38.0195</w><h>27.0</h><angle>0.01</angle></robndbox></object><object><type>robndbox</type><name>sheep</name><pose>Unspecified</pose><truncated>0</truncated><difficult>0</difficult><robndbox><cx>1532.0692</cx><cy>1241.8242</cy><w>43.7866</w><h>27.45</h><angle>2.491593</angle></robndbox></object><object><type>robndbox</type><name>sheep</name><pose>Unspecified</pose><truncated>0</truncated><difficult>0</difficult><robndbox><cx>1201.0129</cx><cy>1571.2274</cy><w>39.3784</w><h>31.8361</h><angle>0.481593</angle></robndbox></object><object><type>robndbox</type><name>sheep</name><pose>Unspecified</pose><truncated>0</truncated><difficult>0</difficult><robndbox><cx>1223.2832</cx><cy>1700.5028</cy><w>53.7317</w><h>41.0824</h><angle>0.78</angle></robndbox></object><object><type>robndbox</type><name>sheep</name><pose>Unspecified</pose><truncated>0</truncated><difficult>0</difficult><robndbox><cx>1197.9548</cx><cy>1535.5</cy><w>35.028</w><h>20.7267</h><angle>1.02</angle></robndbox></object><object><type>robndbox</type><name>sheep</name><pose>Unspecified</pose><truncated>0</truncated><difficult>0</difficult><robndbox><cx>2517.872</cx><cy>759.2527</cy><w>19.8062</w><h>29.6935</h><angle>1.431593</angle></robndbox></object><object><type>robndbox</type><name>sheep</name><pose>Unspecified</pose><truncated>0</truncated><difficult>0</difficult><robndbox><cx>1462.444</cx><cy>1296.0</cy><w>51.2933</w><h>22.1631</h><angle>2.701593</angle></robndbox></object><object><type>robndbox</type><name>sheep</name><pose>Unspecified</pose><truncated>0</truncated><difficult>0</difficult><robndbox><cx>1341.3267</cx><cy>1519.7308</cy><w>24.7384</w><h>38.5127</h><angle>0.18</angle></robndbox></object><object><type>robndbox</type><name>sheep</name><pose>Unspecified</pose><truncated>0</truncated><difficult>0</difficult><robndbox><cx>2266.9552</cx><cy>784.5</cy><w>42.721</w><h>23.6386</h><angle>0.32</angle></robndbox></object><object><type>robndbox</type><name>sheep</name><pose>Unspecified</pose><truncated>0</truncated><difficult>0</difficult><robndbox><cx>490.0248</cx><cy>1873.0387</cy><w>69.5849</w><h>34.875</h><angle>3.071593</angle></robndbox></object><object><type>robndbox</type><name>sheep</name><pose>Unspecified</pose><truncated>0</truncated><difficult>0</difficult><robndbox><cx>581.1107</cx><cy>1878.1642</cy><w>51.0274</w><h>29.7457</h><angle>2.961593</angle></robndbox></object><object><type>robndbox</type><name>sheep</name><pose>Unspecified</pose><truncated>0</truncated><difficult>0</difficult><robndbox><cx>1038.6805</cx><cy>1755.0039</cy><w>40.4106</w><h>73.967</h><angle>0.82</angle></robndbox></object><object><type>robndbox</type><name>sheep</name><pose>Unspecified</pose><truncated>0</truncated><difficult>0</difficult><robndbox><cx>3448.46</cx><cy>348.5</cy><w>28.9785</w><h>17.0</h><angle>0.0</angle></robndbox></object><object><type>robndbox</type><name>sheep</name><pose>Unspecified</pose><truncated>0</truncated><difficult>0</difficult><robndbox><cx>949.4571</cx><cy>1828.0</cy><w>38.9892</w><h>66.0</h><angle>0.51</angle></robndbox></object><object><type>robndbox</type><name>sheep</name><pose>Unspecified</pose><truncated>0</truncated><difficult>0</difficult><robndbox><cx>2450.4517</cx><cy>716.0</cy><w>33.0</w><h>18.0</h><angle>0.0</angle></robndbox></object><object><type>robndbox</type><name>sheep</name><pose>Unspecified</pose><truncated>0</truncated><difficult>0</difficult><robndbox><cx>2257.9406</cx><cy>71.0</cy><w>25.9827</w><h>18.0</h><angle>0.0</angle></robndbox></object><object><type>robndbox</type><name>sheep</name><pose>Unspecified</pose><truncated>0</truncated><difficult>0</difficult><robndbox><cx>2669.4854</cx><cy>237.5</cy><w>22.9708</w><h>15.0</h><angle>0.0</angle></robndbox></object><object><type>robndbox</type><name>sheep</name><pose>Unspecified</pose><truncated>0</truncated><difficult>0</difficult><robndbox><cx>3352.505</cx><cy>66.1022</cy><w>20.9787</w><h>12.624</h><angle>2.941593</angle></robndbox></object><object><type>robndbox</type><name>sheep</name><pose>Unspecified</pose><truncated>0</truncated><difficult>0</difficult><robndbox><cx>1861.461</cx><cy>1055.0</cy><w>30.9764</w><h>20.0</h><angle>0.0</angle></robndbox></object><object><type>robndbox</type><name>sheep</name><pose>Unspecified</pose><truncated>0</truncated><difficult>0</difficult><robndbox><cx>877.5105</cx><cy>1894.2598</cy><w>41.1556</w><h>57.4892</h><angle>2.941593</angle></robndbox></object><object><type>robndbox</type><name>sheep</name><pose>Unspecified</pose><truncated>0</truncated><difficult>0</difficult><robndbox><cx>829.156</cx><cy>1940.6406</cy><w>30.7617</w><h>50.0398</h><angle>2.941593</angle></robndbox></object><object><type>robndbox</type><name>sheep</name><pose>Unspecified</pose><truncated>0</truncated><difficult>0</difficult><robndbox><cx>832.9694</cx><cy>1988.0908</cy><w>59.0072</w><h>33.7418</h><angle>1.22</angle></robndbox></object><object><type>robndbox</type><name>sheep</name><pose>Unspecified</pose><truncated>0</truncated><difficult>0</difficult><robndbox><cx>1693.3969</cx><cy>1298.5</cy><w>41.0</w><h>25.0</h><angle>0.0</angle></robndbox></object><object><type>robndbox</type><name>sheep</name><pose>Unspecified</pose><truncated>0</truncated><difficult>0</difficult><robndbox><cx>81.5</cx><cy>1276.3473</cy><w>39.0</w><h>25.0</h><angle>0.0</angle></robndbox></object></annotation>